ssrfmap/__init__.py
ssrfmap/cli.py
ssrfmap/core/__init__.py
ssrfmap/core/config.py
ssrfmap/core/handler.py
ssrfmap/core/requester.py
ssrfmap/core/ssrf.py
ssrfmap/core/utils.py
ssrfmap/handlers/__init__.py
ssrfmap/handlers/http.py
ssrfmap/modules/__init__.py
ssrfmap/modules/alibaba.py
ssrfmap/modules/aws.py
ssrfmap/modules/consul.py
ssrfmap/modules/custom.py
ssrfmap/modules/digitalocean.py
ssrfmap/modules/docker.py
ssrfmap/modules/fastcgi.py
ssrfmap/modules/gce.py
ssrfmap/modules/github.py
ssrfmap/modules/httpcollaborator.py
ssrfmap/modules/memcache.py
ssrfmap/modules/mysql.py
ssrfmap/modules/networkscan.py
ssrfmap/modules/portscan.py
ssrfmap/modules/readfiles.py
ssrfmap/modules/redis.py
ssrfmap/modules/smbhash.py
ssrfmap/modules/smtp.py
ssrfmap/modules/socksproxy.py
ssrfmap/modules/template.py
ssrfmap/modules/tomcat.py
ssrfmap/modules/zabbix.py
levo_ssrfmap-0.1.12.dist-info/entry_points.txt
levo_ssrfmap-0.1.12.dist-info/LICENSE
levo_ssrfmap-0.1.12.dist-info/WHEEL
levo_ssrfmap-0.1.12.dist-info/METADATA
levo_ssrfmap-0.1.12.dist-info/RECORD
